<xml version="1.0">
<dashboard>
	<static-widget class="edu.wpi.first.smartdashboard.gui.elements.Image">
		<location x="927" y="250"/>
		<width>117</width>
		<height>115</height>
		<property name="Image File" value="C:\FRC\target.png"/>
		<property name="Maintain Aspect Ratio" value="true"/>
	</static-widget>
	<widget field="Auto mode" type="String Chooser" class="edu.wpi.first.smartdashboard.gui.elements.Chooser">
		<location x="0" y="225"/>
	</widget>
	<widget field="Autonomous Command" type="Command" class="edu.wpi.first.smartdashboard.gui.elements.CommandButton">
		<location x="6" y="90"/>
	</widget>
	<widget field="Use Recorded Autonomous" type="Boolean" class="edu.wpi.first.smartdashboard.gui.elements.CheckBox">
		<location x="183" y="408"/>
	</widget>
	<static-widget class="edu.wpi.first.smartdashboard.gui.elements.Label">
		<location x="48" y="408"/>
		<property name="Text" value="Use Recorded Autonomous?"/>
	</static-widget>
	<widget field="AmIWorking?" type="String" class="edu.wpi.first.smartdashboard.gui.elements.TextBox">
		<location x="0" y="0"/>
	</widget>
	<widget field="GoToLevelIfStatement" type="Number" class="edu.wpi.first.smartdashboard.gui.elements.TextBox">
		<location x="0" y="63"/>
	</widget>
	<widget field="LevelEncPos" type="Number" class="edu.wpi.first.smartdashboard.gui.elements.TextBox">
		<location x="0" y="42"/>
	</widget>
	<widget field="levelTo" type="Number" class="edu.wpi.first.smartdashboard.gui.elements.TextBox">
		<location x="0" y="21"/>
	</widget>
	<widget field="Record Autonomous" type="Boolean" class="edu.wpi.first.smartdashboard.gui.elements.BooleanBox">
		<location x="213" y="497"/>
		<height>15</height>
	</widget>
	<widget field="Save Autonomous" type="Boolean" class="edu.wpi.first.smartdashboard.gui.elements.BooleanBox">
		<location x="224" y="528"/>
	</widget>
	<widget field="Play Loaded Autonomous" type="Boolean" class="edu.wpi.first.smartdashboard.gui.elements.BooleanBox">
		<location x="189" y="514"/>
	</widget>
	<widget field="Load Autonomous" type="Boolean" class="edu.wpi.first.smartdashboard.gui.elements.BooleanBox">
		<location x="224" y="544"/>
	</widget>
	<widget field="Flip Motors" type="Command" class="edu.wpi.first.smartdashboard.gui.elements.CommandButton">
		<location x="208" y="297"/>
	</widget>
	<widget field="Rotate Angle" type="Command" class="edu.wpi.first.smartdashboard.gui.elements.CommandButton">
		<location x="209" y="320"/>
	</widget>
	<widget field="Move Forward" type="Command" class="edu.wpi.first.smartdashboard.gui.elements.CommandButton">
		<location x="208" y="345"/>
	</widget>
	<widget field="GoToLevel 3" type="Command" class="edu.wpi.first.smartdashboard.gui.elements.CommandButton">
		<location x="5" y="201"/>
	</widget>
	<widget field="GoToLevel 2" type="Command" class="edu.wpi.first.smartdashboard.gui.elements.CommandButton">
		<location x="5" y="176"/>
	</widget>
	<widget field="GoToLevel 1" type="Command" class="edu.wpi.first.smartdashboard.gui.elements.CommandButton">
		<location x="5" y="153"/>
	</widget>
	<widget field="GoToLevel 0" type="Command" class="edu.wpi.first.smartdashboard.gui.elements.CommandButton">
		<location x="5" y="128"/>
	</widget>
	<widget field="shoot" type="Command" class="edu.wpi.first.smartdashboard.gui.elements.CommandButton">
		<location x="208" y="272"/>
	</widget>
	<widget field="Autonomous Selection" type="String Chooser" class="edu.wpi.first.smartdashboard.gui.elements.Chooser">
		<location x="92" y="284"/>
	</widget>
	<widget field="Scheduler" type="Scheduler" class="edu.wpi.first.smartdashboard.gui.elements.Scheduler">
		<location x="516" y="539"/>
	</widget>
	<widget field="Recorded Selection" type="String Chooser" class="edu.wpi.first.smartdashboard.gui.elements.Chooser">
		<location x="2" y="282"/>
	</widget>
	<widget field="Axis Level right" type="Number" class="edu.wpi.first.smartdashboard.gui.elements.TextBox">
		<location x="646" y="10"/>
	</widget>
	<widget field="Winch Pos" type="Number" class="edu.wpi.first.smartdashboard.gui.elements.TextBox">
		<location x="1145" y="32"/>
	</widget>
	<widget field="Combined Enc." type="Number" class="edu.wpi.first.smartdashboard.gui.elements.TextBox">
		<location x="322" y="46"/>
	</widget>
	<widget field="laser" type="Number" class="edu.wpi.first.smartdashboard.gui.elements.TextBox">
		<location x="915" y="60"/>
	</widget>
	<widget field="Winch Motor Value" type="Number" class="edu.wpi.first.smartdashboard.gui.elements.TextBox">
		<location x="1104" y="0"/>
	</widget>
	<widget field="Gyro.Pitch" type="Number" class="edu.wpi.first.smartdashboard.gui.elements.TextBox">
		<location x="832" y="32"/>
	</widget>
	<widget field="Right Encoder" type="Number" class="edu.wpi.first.smartdashboard.gui.elements.TextBox">
		<location x="323" y="23"/>
	</widget>
	<widget field="Servo val" type="Number" class="edu.wpi.first.smartdashboard.gui.elements.TextBox">
		<location x="973" y="0"/>
	</widget>
	<widget field="ProximitySensor" type="Number" class="edu.wpi.first.smartdashboard.gui.elements.TextBox">
		<location x="976" y="32"/>
	</widget>
	<widget field="Gyro.Roll" type="Number" class="edu.wpi.first.smartdashboard.gui.elements.TextBox">
		<location x="780" y="56"/>
	</widget>
	<widget field="Gyro.Yaw" type="Number" class="edu.wpi.first.smartdashboard.gui.elements.TextBox">
		<location x="503" y="5"/>
	</widget>
	<widget field="Axis Level left" type="Number" class="edu.wpi.first.smartdashboard.gui.elements.TextBox">
		<location x="812" y="6"/>
	</widget>
	<widget field="Left Encoder" type="Number" class="edu.wpi.first.smartdashboard.gui.elements.TextBox">
		<location x="327" y="3"/>
	</widget>
	<widget field="RecordableAutonomous ID" type="String" class="edu.wpi.first.smartdashboard.gui.elements.TextBox">
		<location x="0" y="540"/>
	</widget>
	<static-widget class="edu.wpi.first.smartdashboard.gui.elements.Image">
		<location x="0" y="0"/>
		<property name="Image File" value="C:\Users\Zach\git\Robot_2016\smartdashboardbg.png"/>
	</static-widget>
	<static-widget class="edu.wpi.first.smartdashboard.gui.elements.ConnectionIndicator">
		<location x="614" y="118"/>
		<width>59</width>
		<height>83</height>
		<property name="Connection Color" value="255.55.0.255"/>
		<property name="No Connection Color" value="51.51.51.255"/>
	</static-widget>
	<static-widget class="edu.wpi.first.smartdashboard.gui.elements.ConnectionIndicator">
		<location x="590" y="63"/>
		<width>106</width>
		<property name="Connection Color" value="0.255.51.255"/>
		<property name="No Connection Color" value="0.0.102.255"/>
	</static-widget>
	<static-widget class="edu.wpi.first.smartdashboard.gui.elements.WebcamViewerExtension">
		<location x="642" y="81"/>
		<width>638</width>
		<height>479</height>
	</static-widget>
	<static-widget class="edu.wpi.first.smartdashboard.gui.elements.Label">
		<location x="48" y="408"/>
		<property name="Text" value="Use Recorded Autonomous?"/>
	</static-widget>
	<static-widget class="edu.wpi.first.smartdashboard.gui.elements.Image">
		<location x="0" y="0"/>
		<property name="Image File" value="C:\Users\Brendan\git\Robot_2016\smartdashboardbg.png"/>
	</static-widget>
	<static-widget class="edu.wpi.first.smartdashboard.gui.elements.ConnectionIndicator">
		<location x="614" y="118"/>
		<width>59</width>
		<height>83</height>
		<property name="Connection Color" value="255.55.0.255"/>
		<property name="No Connection Color" value="51.51.51.255"/>
	</static-widget>
	<static-widget class="edu.wpi.first.smartdashboard.gui.elements.ConnectionIndicator">
		<location x="590" y="63"/>
		<width>106</width>
		<property name="Connection Color" value="0.255.51.255"/>
		<property name="No Connection Color" value="0.0.102.255"/>
	</static-widget>
	<static-widget class="edu.wpi.first.smartdashboard.gui.elements.WebcamViewerExtension">
		<location x="642" y="81"/>
		<width>638</width>
		<height>479</height>
	</static-widget>
</dashboard>
<live-window>
</live-window>
	<hidden field="DEBUG2"/>
	<hidden field="DEBUG"/>
</xml>